sqs_workers/__init__.py
sqs_workers/async_task.py
sqs_workers/backoff_policies.py
sqs_workers/batching.py
sqs_workers/codecs.py
sqs_workers/config.py
sqs_workers/context.py
sqs_workers/core.py
sqs_workers/deadletter_queue.py
sqs_workers/exceptions.py
sqs_workers/memory_sqs.py
sqs_workers/processors.py
sqs_workers/py.typed
sqs_workers/queue.py
sqs_workers/shutdown_policies.py
sqs_workers/sqs_env.py
sqs_workers/sqs_manage.py
sqs_workers/utils.py
sqs_workers-0.6.0.dist-info/METADATA
sqs_workers-0.6.0.dist-info/WHEEL
sqs_workers-0.6.0.dist-info/licenses/LICENSE
sqs_workers-0.6.0.dist-info/RECORD
