Metadata-Version: 2.4
Name: sqs-workers
Version: 0.6.0
Summary: An opinionated queue processor for Amazon SQS
Project-URL: Homepage, https://github.com/Doist/sqs-workers
Author-email: Doist Developers <dev@doist.com>
License-Expression: MIT
License-File: LICENSE
Classifier: Development Status :: 5 - Production/Stable
Classifier: License :: OSI Approved :: MIT License
Classifier: Programming Language :: Python
Classifier: Programming Language :: Python :: 3
Classifier: Programming Language :: Python :: 3.8
Classifier: Programming Language :: Python :: 3.9
Classifier: Programming Language :: Python :: 3.10
Classifier: Programming Language :: Python :: 3.11
Classifier: Programming Language :: Python :: 3.12
Requires-Python: <3.14,>=3.9
Requires-Dist: boto3<2,>=1.37.33
